meshoid/Meshoid.py
meshoid/__init__.py
meshoid/derivatives.py
meshoid/glass.py
meshoid/glass_64.npy
meshoid/grid_deposition.py
meshoid/kernel_density.py
meshoid/load_from_snapshot.py
meshoid/radiation/__init__.py
meshoid/radiation/dust.py
meshoid/radiation/mbb_jax.py
meshoid/radiation/modified_blackbody.py
meshoid/radiation/radtransfer.py
meshoid/radiation/opacity_tables/hensley_draine_2022_astrodust_opacity.dat
meshoid/radiation/opacity_tables/semenov2003/Comp_aggregates/1.dat
meshoid/radiation/opacity_tables/semenov2003/Comp_aggregates/2.dat
meshoid/radiation/opacity_tables/semenov2003/Comp_aggregates/3.dat
meshoid/radiation/opacity_tables/semenov2003/Comp_aggregates/4.dat
meshoid/radiation/opacity_tables/semenov2003/Comp_aggregates/5.dat
meshoid/radiation/opacity_tables/semenov2003/Comp_spheres/1.dat
meshoid/radiation/opacity_tables/semenov2003/Comp_spheres/2.dat
meshoid/radiation/opacity_tables/semenov2003/Comp_spheres/3.dat
meshoid/radiation/opacity_tables/semenov2003/Comp_spheres/4.dat
meshoid/radiation/opacity_tables/semenov2003/Comp_spheres/5.dat
meshoid/radiation/opacity_tables/semenov2003/Hom_aggregates/1.dat
meshoid/radiation/opacity_tables/semenov2003/Hom_aggregates/2.dat
meshoid/radiation/opacity_tables/semenov2003/Hom_aggregates/3.dat
meshoid/radiation/opacity_tables/semenov2003/Hom_aggregates/4.dat
meshoid/radiation/opacity_tables/semenov2003/Hom_aggregates/5.dat
meshoid/radiation/opacity_tables/semenov2003/Hom_spheres/1.dat
meshoid/radiation/opacity_tables/semenov2003/Hom_spheres/2.dat
meshoid/radiation/opacity_tables/semenov2003/Hom_spheres/3.dat
meshoid/radiation/opacity_tables/semenov2003/Hom_spheres/4.dat
meshoid/radiation/opacity_tables/semenov2003/Hom_spheres/5.dat
meshoid/radiation/opacity_tables/semenov2003/Multishell_spheres/1.dat
meshoid/radiation/opacity_tables/semenov2003/Multishell_spheres/2.dat
meshoid/radiation/opacity_tables/semenov2003/Multishell_spheres/3.dat
meshoid/radiation/opacity_tables/semenov2003/Multishell_spheres/4.dat
meshoid-1.48.7.dist-info/METADATA
meshoid-1.48.7.dist-info/WHEEL
meshoid-1.48.7.dist-info/top_level.txt
meshoid-1.48.7.dist-info/RECORD
