Metadata-Version: 2.4
Name: meshoid
Version: 1.48.7
Summary: Package for analysis of meshless simulation data
Home-page: http://github.com/mikegrudic/meshoid
Author: Mike Grudić
Author-email: mike.grudich@gmail.com
License: MIT
Project-URL: Bug Tracker, https://github.com/mikegrudic/meshoid
Classifier: Programming Language :: Python :: 3
Classifier: License :: OSI Approved :: MIT License
Classifier: Operating System :: OS Independent
Requires-Python: >=3.6
Dynamic: author
Dynamic: author-email
Dynamic: classifier
Dynamic: home-page
Dynamic: license
Dynamic: project-url
Dynamic: requires-python
Dynamic: summary
